{"kode":"PBNL0324110001","tbeli":[[{"IDPERUSAHAAN":"2","IDBELI":"2","KODEBELI":"PBNL0324110001","IDPO":"0","KODEPO":"-","NOINVOICESUPPLIER":"","IDLOKASI":"3","IDSUPPLIER":"91","IDSYARATBAYAR":"8","TGLJATUHTEMPO":"2024-11-24","TGLTRANS":"2024-11-23","TGLENTRY":"2024-11-23","JAMENTRY":"11:26:07","USERENTRY":"ADMINLITTLETWISTY","TGLBATAL":null,"JAMBATAL":null,"USERBATAL":null,"ALASANBATAL":null,"TOTAL":null,"PPNRP":null,"PPH22RP":null,"PEMBULATAN":null,"GRANDTOTAL":null,"CATATAN":null,"STATUS":"S","CLOSING":"0"}]],"tbelidtl":[[{"IDPERUSAHAAN":"2","IDBELI":"2","KODEBELI":"PBNL0324110001","IDPO":"0","ADANPWP":"0","IDBARANG":"42","IDCURRENCY":"1","URUTAN":"1","JML":"1.0000","JMLBONUS":"0.0000","SATUAN":"PAIR","SATUANUTAMA":"","KONVERSI":"0.0000","HARGA":"0.0000","DISCPERSEN":"0","DISC":"0.0000","SUBTOTAL":"0.0000","NILAIKURS":null,"HARGAKURS":"0.0000","DISCKURS":"0.0000","SUBTOTALKURS":"0.0000","PAKAIPPN":"0","PPNPERSEN":null,"PPNRP":"0.0000","PPH22PERSEN":null,"PPH22RP":null,"IDAKUNBIAYA":"0","IDAKUNHUTANG":"0","TUTUP":"0"}]],"ip":"103.161.196.254","macaddress":""}