{"kode":"B0308","mbarang":[[{"IDPERUSAHAAN":"2","IDBARANG":"326","IDBARANGSHOPEE":"","IDBARANGTIKTOK":"","IDBARANGLAZADA":"","IDINDUKBARANGSHOPEE":"","IDINDUKBARANGTIKTOK":"","IDINDUKBARANGLAZADA":"","BOOSTSHOPEE":"0","KODEBARANG":"B0308","STOK":"1","JUAL":null,"KONSINYASI":null,"FNB":null,"NAMABARANG":"LAP SEPATU","KATEGORI":"Lap Sepatu","KATEGORIONLINE":"PEMBUNGKUS KADO DAN KEMASAN","DESKRIPSI":"Lap SepatuLap SepatuLap Sepatu","WARNA":"","SIZE":"0","BERAT":"1","PANJANG":"1","LEBAR":"1","TINGGI":"1","AKUNPERSEDIAAN":null,"AKUNHPP":null,"PARTNUMBER":null,"BARCODE":"LT-123123","SATUAN":"PAIR","SATUAN2":"PAIR","SATUAN3":"","KONVERSI1":"1.0000","KONVERSI2":"1.0000","HARGABELI":"10000.0000","HARGAJUAL":"1000.0000","SKUGOJEK":"","SKUGRAB":"","SKUTOKPED":"","SKUSHOPEE":"LT-123123","SKUTIKTOK":"LT-123123","SKULAZADA":"LT-123123","LIMITMIN":"0.0000","LIMITMAX":"99000.0000","GAMBAR":null,"CATATAN":"","URUTANTAMPIL":"Y1","USERENTRY":"ADMINLITTLETWISTY","USERUBAH":null,"USERHAPUS":null,"TGLENTRY":"2025-08-22","TGLUBAH":null,"TGLHAPUS":null,"STATUS":"1"}]],"ip":"158.140.171.49","macaddress":""}