{"kode":"ADJ\/L02\/250328\/0001","tpenyesuaianstok":[[{"IDPERUSAHAAN":"2","IDPENYESUAIANSTOK":"109","KODEPENYESUAIANSTOK":"ADJ\/L02\/250328\/0001","IDLOKASI":"2","IDOPNAMESTOK":"0","TGLTRANS":"2025-03-28","CATATAN":"RETUR SHOPEE","TGLENTRY":"2025-03-28","JAMENTRY":"11:14:24","USERENTRY":"ADMINDIANA","TGLBATAL":null,"JAMBATAL":null,"USERBATAL":null,"ALASANBATAL":null,"STATUS":"S","CLOSING":"0"}]],"tpenyesuaianstokdtl":[[{"IDPERUSAHAAN":"2","IDPENYESUAIANSTOK":"109","KODEPENYESUAIANSTOK":"ADJ\/L02\/250328\/0001","IDBARANG":"104","URUTAN":"0","JML":"6.0000","SELISIH":"1.0000","SATUAN":"PAIR","SATUANUTAMA":"PAIR","KONVERSI":"1.0000","HARGA":"90000.0000","SUBTOTAL":"540000.0000"},{"IDPERUSAHAAN":"2","IDPENYESUAIANSTOK":"109","KODEPENYESUAIANSTOK":"ADJ\/L02\/250328\/0001","IDBARANG":"144","URUTAN":"0","JML":"6.0000","SELISIH":"1.0000","SATUAN":"PAIR","SATUANUTAMA":"PAIR","KONVERSI":"1.0000","HARGA":"80000.0000","SUBTOTAL":"480000.0000"},{"IDPERUSAHAAN":"2","IDPENYESUAIANSTOK":"109","KODEPENYESUAIANSTOK":"ADJ\/L02\/250328\/0001","IDBARANG":"148","URUTAN":"0","JML":"5.0000","SELISIH":"1.0000","SATUAN":"PAIR","SATUANUTAMA":"PAIR","KONVERSI":"1.0000","HARGA":"80000.0000","SUBTOTAL":"400000.0000"}]],"ip":"158.140.179.156","macaddress":""}