{"kode":"TFL0225060001","ttransfer":[[{"IDPERUSAHAAN":"2","IDTRANSFER":"157","KODETRANSFER":"TFL0225060001","IDLOKASIASAL":"2","IDLOKASITUJUAN":"1","IDCUSTOMER":"0","TGLTRANS":"2025-06-10","TGLKIRIM":"2025-06-10","TGLENTRY":"2025-06-10","JAMENTRY":"13:11:58","USERENTRY":"ADMINKARINA","TGLBATAL":null,"JAMBATAL":null,"USERBATAL":null,"ALASANBATAL":null,"CATATAN":null,"STATUS":"S","CLOSING":"0"}]],"ttransferdtl":[[{"IDPERUSAHAAN":"2","IDTRANSFER":"157","KODETRANSFER":"TFL0225060001","IDBARANG":"107","URUTAN":"1","JML":"2.0000","TERPENUHI":"0.0000","SISA":"2.0000","HARGA":"0.0000","SATUAN":"PAIR","SATUANUTAMA":"","KONVERSI":"0.0000","TUTUP":"0","CATATAN":null}]],"ip":"103.47.133.85","macaddress":""}